dev_tools/__init__.py
dev_tools/template_server.py
dev_tools-0.0.3.dist-info/LICENSE
dev_tools-0.0.3.dist-info/METADATA
dev_tools-0.0.3.dist-info/WHEEL
dev_tools-0.0.3.dist-info/entry_points.txt
dev_tools-0.0.3.dist-info/top_level.txt
dev_tools-0.0.3.dist-info/RECORD
